__init__.py
envplay.py
ldnsexplorer/DNS_APP.py
ldnsexplorer/__init__.py
ldnsexplorer/__main__.py
ldnsexplorer/find_local_resolver.py
ldnsexplorer/measure_dns.py
ldnsexplorer/measure_tcp.py
ldnsexplorer/tcp_client.py
ldnsexplorer-1.1.0.dist-info/METADATA
ldnsexplorer-1.1.0.dist-info/WHEEL
ldnsexplorer-1.1.0.dist-info/top_level.txt
ldnsexplorer-1.1.0.dist-info/RECORD
