Metadata-Version: 2.1
Name: ldnsexplorer
Version: 1.1.0
Summary: A public DNS resolver explorer
Author: handsome guy
Classifier: Programming Language :: Python
Classifier: Operating System :: OS Independent
Requires-Python: >=3
Requires-Dist: matplotlib
Requires-Dist: dnspython
